gavathilang_cli.py
gavathilang_cli-0.1.dist-info/METADATA
gavathilang_cli-0.1.dist-info/WHEEL
gavathilang_cli-0.1.dist-info/entry_points.txt
gavathilang_cli-0.1.dist-info/top_level.txt
gavathilang_cli-0.1.dist-info/RECORD
