Metadata-Version: 2.1
Name: gavathilang-cli
Version: 0.1
Summary: A CLI tool for GavathiLang
Home-page: https://github.com/yourusername/gavathilang-cli
Author: Sonu Vishwakarma
Author-email: sonu.v.s.771984@gmail.com
License: UNKNOWN
Platform: UNKNOWN
Classifier: Programming Language :: Python :: 3
Classifier: Operating System :: OS Independent
Requires-Python: >=3.6
